alodenhftmarketclient/__init__.py
alodenhftmarketclient/client.py
alodenhftmarketclient/protocol.py
alodenhftmarketclient-0.1.4.dist-info/METADATA
alodenhftmarketclient-0.1.4.dist-info/WHEEL
alodenhftmarketclient-0.1.4.dist-info/RECORD
