Metadata-Version: 2.1
Name: alodenhftmarketclient
Version: 0.1.4
Summary: Python client for the HFT Simulator bridge server (REST + WebSockets helpers)
Home-page: https://hft-simulator.fr
License: Proprietary
Author: Aloden
Requires-Python: >=3.10,<4.0
Classifier: License :: Other/Proprietary License
Classifier: Programming Language :: Python :: 3
Classifier: Programming Language :: Python :: 3.10
Classifier: Programming Language :: Python :: 3.11
Classifier: Programming Language :: Python :: 3.12
Requires-Dist: httpx (>=0.24)
Requires-Dist: websockets (>=10)
Project-URL: Repository, https://github.com/Al0den/hft-simulator
